twyclip/__init__.py
twyclip/twyclip.py
twyclip-1.0.2.dist-info/LICENSE
twyclip-1.0.2.dist-info/METADATA
twyclip-1.0.2.dist-info/WHEEL
twyclip-1.0.2.dist-info/top_level.txt
twyclip-1.0.2.dist-info/RECORD
