Metadata-Version: 2.1
Name: twyclip
Version: 1.0.2
Summary: TwyClip is a Python library for get Twitch clip download link.
Home-page: UNKNOWN
Author: John Doe
License: The Unlicense (Unlicense)
Keywords: twitch
Platform: UNKNOWN
Requires-Python: >=3.8
License-File: LICENSE
Requires-Dist: requests
